callixir/__init__.py
callixir/_command.py
callixir/_command_meta.py
callixir/_core.py
callixir/_exceptions.py
callixir/_fingerprint.py
callixir/_formats.py
callixir/dispatchers/__init__.py
callixir/dispatchers/async_dispatcher.py
callixir/dispatchers/sync_dispatcher.py
callixir/shells/__init__.py
callixir/shells/async_simple_shell.py
callixir/shells/simple_shell.py
callixir-0.1.0.dist-info/licenses/LICENSE
callixir-0.1.0.dist-info/METADATA
callixir-0.1.0.dist-info/WHEEL
callixir-0.1.0.dist-info/RECORD
