Metadata-Version: 2.4
Name: callixir
Version: 0.1.0
Summary: A Python module for calling functions by string with argument support
License-File: LICENSE
Author: Vordy
Author-email: vorklab@outlook.com
Requires-Python: >=3.12
Classifier: Programming Language :: Python :: 3
Classifier: Programming Language :: Python :: 3.12
Classifier: Programming Language :: Python :: 3.13
Classifier: Programming Language :: Python :: 3.14
